no_profanity/__init__.py
no_profanity/main.py
no_profanity/data/__init__.py
no_profanity/data/config.py
no_profanity-1.1.1.dist-info/licenses/LICENSE
no_profanity-1.1.1.dist-info/METADATA
no_profanity-1.1.1.dist-info/WHEEL
no_profanity-1.1.1.dist-info/top_level.txt
no_profanity-1.1.1.dist-info/RECORD
