Metadata-Version: 2.4
Name: no-profanity
Version: 1.1.1
Summary: A library using regex manipulation to detect and block profanity in strings.
Home-page: https://github.com/Gl1tch3dL1m3/no-profanity
Author: GlitchedLime
Author-email: gabcosamuel8@gmail.com
Classifier: Programming Language :: Python :: 3
Classifier: Operating System :: OS Independent
License-File: LICENSE
Dynamic: author
Dynamic: author-email
Dynamic: classifier
Dynamic: description
Dynamic: description-content-type
Dynamic: home-page
Dynamic: license-file
Dynamic: summary
